pymuv/__init__.py
pymuv/context.py
pymuv/errors.py
pymuv/grammar.py
pymuv/lvalue.py
pymuv/muvnodes.py
pymuv/parsefile.py
pymuv/settable.py
pymuv/visitor.py
pymuv/incls/fb6/ansi
pymuv/incls/fb6/argparse
pymuv/incls/fb6/array
pymuv/incls/fb6/conn
pymuv/incls/fb6/debug
pymuv/incls/fb6/descr
pymuv/incls/fb6/event
pymuv/incls/fb6/gui
pymuv/incls/fb6/io
pymuv/incls/fb6/lock
pymuv/incls/fb6/match
pymuv/incls/fb6/math
pymuv/incls/fb6/mcp
pymuv/incls/fb6/obj
pymuv/incls/fb6/prims
pymuv/incls/fb6/proc
pymuv/incls/fb6/prog
pymuv/incls/fb6/prop
pymuv/incls/fb6/regex
pymuv/incls/fb6/stdlib
pymuv/incls/fb6/str
pymuv/incls/fb6/sys
pymuv/incls/fb6/time
pymuv/incls/fb6/type
pymuv/incls/fb7/ansi
pymuv/incls/fb7/argparse
pymuv/incls/fb7/array
pymuv/incls/fb7/conn
pymuv/incls/fb7/debug
pymuv/incls/fb7/descr
pymuv/incls/fb7/event
pymuv/incls/fb7/gui
pymuv/incls/fb7/io
pymuv/incls/fb7/lock
pymuv/incls/fb7/match
pymuv/incls/fb7/math
pymuv/incls/fb7/mcp
pymuv/incls/fb7/obj
pymuv/incls/fb7/prims
pymuv/incls/fb7/proc
pymuv/incls/fb7/prog
pymuv/incls/fb7/prop
pymuv/incls/fb7/regex
pymuv/incls/fb7/stdlib
pymuv/incls/fb7/str
pymuv/incls/fb7/sys
pymuv/incls/fb7/time
pymuv/incls/fb7/type
pymuv-0.9.9.dist-info/LICENSE
pymuv-0.9.9.dist-info/METADATA
pymuv-0.9.9.dist-info/WHEEL
pymuv-0.9.9.dist-info/entry_points.txt
pymuv-0.9.9.dist-info/top_level.txt
pymuv-0.9.9.dist-info/RECORD
