Metadata-Version: 2.1
Name: pymuv
Version: 0.9.9
Summary: A python implementation of the MUV 2.0 to FuzzBall MUCK MUF compiler.
Home-page: https://github.com/revarbat/pymuv
Author: Revar Desmera
Author-email: revarbat@gmail.com
License: MIT License
Download-URL: https://github.com/revarbat/pymuv/archive/master.zip
Keywords: muv muf muck compiler
Platform: UNKNOWN
Classifier: Development Status :: 4 - Beta
Classifier: Environment :: Console
Classifier: Intended Audience :: Developers
Classifier: License :: OSI Approved :: MIT License
Classifier: Operating System :: MacOS :: MacOS X
Classifier: Operating System :: Microsoft :: Windows
Classifier: Operating System :: POSIX
Classifier: Programming Language :: Python :: 2
Classifier: Programming Language :: Python :: 3
Classifier: Topic :: Software Development :: Code Generators
Classifier: Topic :: Software Development :: Compilers
Classifier: Topic :: Software Development :: Libraries
Classifier: Topic :: Software Development :: Libraries :: Python Modules
Requires-Dist: setuptools
Requires-Dist: Arpeggio (>=1.5)
Requires-Dist: six (>=1.10.0)
